sentry_feishu/__init__.py
sentry_feishu/forms.py
sentry_feishu/plugin.py
sentry_feishu_wx-0.0.7.dist-info/METADATA
sentry_feishu_wx-0.0.7.dist-info/WHEEL
sentry_feishu_wx-0.0.7.dist-info/entry_points.txt
sentry_feishu_wx-0.0.7.dist-info/top_level.txt
sentry_feishu_wx-0.0.7.dist-info/RECORD
