Metadata-Version: 2.1
Name: sentry-feishu-wx
Version: 0.0.7
Summary: A Sentry extension which send errors stats to Feishu
Home-page: https://github.com/chengandpeng/sentry_feishu
Author: chengpeng
Author-email: chengandpeng@gmail.com
License: MIT
Keywords: sentry feishu
Classifier: Programming Language :: Python :: 2.7
Classifier: License :: OSI Approved :: MIT License
Requires-Dist: sentry (>=9.0.0)
Requires-Dist: requests
